[
  {
    "village": "Rambagh",
    "slug": "rambagh",
    "city": "Leh",
    "state": "Ladakh"
  },
  {
    "village": "Gopalkoti",
    "slug": "gopalkoti",
    "city": "Leh",
    "state": "Ladakh"
  },
  {
    "village": "Shyamchaur",
    "slug": "shyamchaur",
    "city": "Leh",
    "state": "Ladakh"
  },
  {
    "village": "Harikoti",
    "slug": "harikoti",
    "city": "Kargil",
    "state": "Ladakh"
  },
  {
    "village": "Agrachaur",
    "slug": "agrachaur",
    "city": "Kargil",
    "state": "Ladakh"
  },
  {
    "village": "Beldhar",
    "slug": "beldhar",
    "city": "Kargil",
    "state": "Ladakh"
  },
  {
    "village": "Kalyanchaur",
    "slug": "kalyanchaur",
    "city": "Leh Block",
    "state": "Ladakh"
  },
  {
    "village": "Vikasdhar",
    "slug": "vikasdhar",
    "city": "Leh Block",
    "state": "Ladakh"
  },
  {
    "village": "Ashokgaon",
    "slug": "ashokgaon",
    "city": "Leh Block",
    "state": "Ladakh"
  },
  {
    "village": "Premdhar",
    "slug": "premdhar",
    "city": "Kargil Rural",
    "state": "Ladakh"
  },
  {
    "village": "Chandragaon",
    "slug": "chandragaon",
    "city": "Kargil Rural",
    "state": "Ladakh"
  },
  {
    "village": "Suryasain",
    "slug": "suryasain",
    "city": "Kargil Rural",
    "state": "Ladakh"
  },
  {
    "village": "Rajgaon",
    "slug": "rajgaon",
    "city": "Leh East",
    "state": "Ladakh"
  },
  {
    "village": "Motisain",
    "slug": "motisain",
    "city": "Leh East",
    "state": "Ladakh"
  },
  {
    "village": "Ramtok",
    "slug": "ramtok",
    "city": "Leh East",
    "state": "Ladakh"
  },
  {
    "village": "Gopalsain",
    "slug": "gopalsain",
    "city": "Kargil West",
    "state": "Ladakh"
  },
  {
    "village": "Shyamtok",
    "slug": "shyamtok",
    "city": "Kargil West",
    "state": "Ladakh"
  },
  {
    "village": "Harigund",
    "slug": "harigund",
    "city": "Kargil West",
    "state": "Ladakh"
  },
  {
    "village": "Agratok",
    "slug": "agratok",
    "city": "Leh North",
    "state": "Ladakh"
  },
  {
    "village": "Belgund",
    "slug": "belgund",
    "city": "Leh North",
    "state": "Ladakh"
  },
  {
    "village": "Kalyanbagh",
    "slug": "kalyanbagh",
    "city": "Leh North",
    "state": "Ladakh"
  },
  {
    "village": "Vikasgund",
    "slug": "vikasgund",
    "city": "Kargil South",
    "state": "Ladakh"
  },
  {
    "village": "Ashokbagh",
    "slug": "ashokbagh",
    "city": "Kargil South",
    "state": "Ladakh"
  },
  {
    "village": "Premkoti",
    "slug": "premkoti",
    "city": "Kargil South",
    "state": "Ladakh"
  },
  {
    "village": "Chandrabagh",
    "slug": "chandrabagh",
    "city": "Leh Central",
    "state": "Ladakh"
  },
  {
    "village": "Suryakoti",
    "slug": "suryakoti",
    "city": "Leh Central",
    "state": "Ladakh"
  },
  {
    "village": "Rajchaur",
    "slug": "rajchaur",
    "city": "Leh Central",
    "state": "Ladakh"
  },
  {
    "village": "Motikoti",
    "slug": "motikoti",
    "city": "Kargil Hills",
    "state": "Ladakh"
  },
  {
    "village": "Ramchaur",
    "slug": "ramchaur",
    "city": "Kargil Hills",
    "state": "Ladakh"
  },
  {
    "village": "Gopaldhar",
    "slug": "gopaldhar",
    "city": "Kargil Hills",
    "state": "Ladakh"
  },
  {
    "village": "Shyamchaur",
    "slug": "shyamchaur",
    "city": "Leh Valley",
    "state": "Ladakh"
  },
  {
    "village": "Haridhar",
    "slug": "haridhar",
    "city": "Leh Valley",
    "state": "Ladakh"
  },
  {
    "village": "Agragaon",
    "slug": "agragaon",
    "city": "Leh Valley",
    "state": "Ladakh"
  },
  {
    "village": "Beldhar",
    "slug": "beldhar",
    "city": "Kargil Uplands",
    "state": "Ladakh"
  },
  {
    "village": "Kalyangaon",
    "slug": "kalyangaon",
    "city": "Kargil Uplands",
    "state": "Ladakh"
  },
  {
    "village": "Vikassain",
    "slug": "vikassain",
    "city": "Kargil Uplands",
    "state": "Ladakh"
  },
  {
    "village": "Ashokgaon",
    "slug": "ashokgaon",
    "city": "Leh Plains",
    "state": "Ladakh"
  },
  {
    "village": "Premsain",
    "slug": "premsain",
    "city": "Leh Plains",
    "state": "Ladakh"
  },
  {
    "village": "Chandratok",
    "slug": "chandratok",
    "city": "Leh Plains",
    "state": "Ladakh"
  },
  {
    "village": "Suryasain",
    "slug": "suryasain",
    "city": "Kargil Green-Belt",
    "state": "Ladakh"
  },
  {
    "village": "Rajtok",
    "slug": "rajtok",
    "city": "Kargil Green-Belt",
    "state": "Ladakh"
  },
  {
    "village": "Motigund",
    "slug": "motigund",
    "city": "Kargil Green-Belt",
    "state": "Ladakh"
  },
  {
    "village": "Ramtok",
    "slug": "ramtok",
    "city": "Leh Agri-Zone",
    "state": "Ladakh"
  },
  {
    "village": "Gopalgund",
    "slug": "gopalgund",
    "city": "Leh Agri-Zone",
    "state": "Ladakh"
  },
  {
    "village": "Shyambagh",
    "slug": "shyambagh",
    "city": "Leh Agri-Zone",
    "state": "Ladakh"
  },
  {
    "village": "Harigund",
    "slug": "harigund",
    "city": "Kargil Industrial-Block",
    "state": "Ladakh"
  },
  {
    "village": "Agrabagh",
    "slug": "agrabagh",
    "city": "Kargil Industrial-Block",
    "state": "Ladakh"
  },
  {
    "village": "Belkoti",
    "slug": "belkoti",
    "city": "Kargil Industrial-Block",
    "state": "Ladakh"
  },
  {
    "village": "Kalyanbagh",
    "slug": "kalyanbagh",
    "city": "Leh Tech-Park",
    "state": "Ladakh"
  },
  {
    "village": "Vikaskoti",
    "slug": "vikaskoti",
    "city": "Leh Tech-Park",
    "state": "Ladakh"
  },
  {
    "village": "Ashokchaur",
    "slug": "ashokchaur",
    "city": "Leh Tech-Park",
    "state": "Ladakh"
  },
  {
    "village": "Premkoti",
    "slug": "premkoti",
    "city": "Kargil Sub-Township",
    "state": "Ladakh"
  },
  {
    "village": "Chandrachaur",
    "slug": "chandrachaur",
    "city": "Kargil Sub-Township",
    "state": "Ladakh"
  },
  {
    "village": "Suryadhar",
    "slug": "suryadhar",
    "city": "Kargil Sub-Township",
    "state": "Ladakh"
  },
  {
    "village": "Rajchaur",
    "slug": "rajchaur",
    "city": "Leh Extension",
    "state": "Ladakh"
  },
  {
    "village": "Motidhar",
    "slug": "motidhar",
    "city": "Leh Extension",
    "state": "Ladakh"
  },
  {
    "village": "Ramgaon",
    "slug": "ramgaon",
    "city": "Leh Extension",
    "state": "Ladakh"
  },
  {
    "village": "Gopaldhar",
    "slug": "gopaldhar",
    "city": "Kargil Bypass",
    "state": "Ladakh"
  },
  {
    "village": "Shyamgaon",
    "slug": "shyamgaon",
    "city": "Kargil Bypass",
    "state": "Ladakh"
  },
  {
    "village": "Harisain",
    "slug": "harisain",
    "city": "Kargil Bypass",
    "state": "Ladakh"
  },
  {
    "village": "Agragaon",
    "slug": "agragaon",
    "city": "Leh Cantonment",
    "state": "Ladakh"
  },
  {
    "village": "Belsain",
    "slug": "belsain",
    "city": "Leh Cantonment",
    "state": "Ladakh"
  },
  {
    "village": "Kalyantok",
    "slug": "kalyantok",
    "city": "Leh Cantonment",
    "state": "Ladakh"
  },
  {
    "village": "Vikassain",
    "slug": "vikassain",
    "city": "Kargil Outer",
    "state": "Ladakh"
  },
  {
    "village": "Ashoktok",
    "slug": "ashoktok",
    "city": "Kargil Outer",
    "state": "Ladakh"
  },
  {
    "village": "Premgund",
    "slug": "premgund",
    "city": "Kargil Outer",
    "state": "Ladakh"
  },
  {
    "village": "Chandratok",
    "slug": "chandratok",
    "city": "Leh Inner",
    "state": "Ladakh"
  },
  {
    "village": "Suryagund",
    "slug": "suryagund",
    "city": "Leh Inner",
    "state": "Ladakh"
  },
  {
    "village": "Rajbagh",
    "slug": "rajbagh",
    "city": "Leh Inner",
    "state": "Ladakh"
  },
  {
    "village": "Motigund",
    "slug": "motigund",
    "city": "Kargil Metro-Hub",
    "state": "Ladakh"
  },
  {
    "village": "Rambagh",
    "slug": "rambagh",
    "city": "Kargil Metro-Hub",
    "state": "Ladakh"
  },
  {
    "village": "Gopalkoti",
    "slug": "gopalkoti",
    "city": "Kargil Metro-Hub",
    "state": "Ladakh"
  },
  {
    "village": "Shyambagh",
    "slug": "shyambagh",
    "city": "Leh Farm-Block",
    "state": "Ladakh"
  },
  {
    "village": "Harikoti",
    "slug": "harikoti",
    "city": "Leh Farm-Block",
    "state": "Ladakh"
  },
  {
    "village": "Agrachaur",
    "slug": "agrachaur",
    "city": "Leh Farm-Block",
    "state": "Ladakh"
  }
]