[
  {
    "village": "Rampur",
    "slug": "rampur",
    "city": "Ludhiana",
    "state": "Punjab"
  },
  {
    "village": "Gopalgaon",
    "slug": "gopalgaon",
    "city": "Ludhiana",
    "state": "Punjab"
  },
  {
    "village": "Shyamkhera",
    "slug": "shyamkhera",
    "city": "Ludhiana",
    "state": "Punjab"
  },
  {
    "village": "Harigaon",
    "slug": "harigaon",
    "city": "Amritsar",
    "state": "Punjab"
  },
  {
    "village": "Agrakhera",
    "slug": "agrakhera",
    "city": "Amritsar",
    "state": "Punjab"
  },
  {
    "village": "Belkhurd",
    "slug": "belkhurd",
    "city": "Amritsar",
    "state": "Punjab"
  },
  {
    "village": "Kalyankhera",
    "slug": "kalyankhera",
    "city": "Jalandhar",
    "state": "Punjab"
  },
  {
    "village": "Vikaskhurd",
    "slug": "vikaskhurd",
    "city": "Jalandhar",
    "state": "Punjab"
  },
  {
    "village": "Ashokbuzurg",
    "slug": "ashokbuzurg",
    "city": "Jalandhar",
    "state": "Punjab"
  },
  {
    "village": "Premkhurd",
    "slug": "premkhurd",
    "city": "Patiala",
    "state": "Punjab"
  },
  {
    "village": "Chandrabuzurg",
    "slug": "chandrabuzurg",
    "city": "Patiala",
    "state": "Punjab"
  },
  {
    "village": "Suryanagar",
    "slug": "suryanagar",
    "city": "Patiala",
    "state": "Punjab"
  },
  {
    "village": "Rajbuzurg",
    "slug": "rajbuzurg",
    "city": "Bathinda",
    "state": "Punjab"
  },
  {
    "village": "Motinagar",
    "slug": "motinagar",
    "city": "Bathinda",
    "state": "Punjab"
  },
  {
    "village": "Ramkalan",
    "slug": "ramkalan",
    "city": "Bathinda",
    "state": "Punjab"
  },
  {
    "village": "Gopalnagar",
    "slug": "gopalnagar",
    "city": "Ajitgarh",
    "state": "Punjab"
  },
  {
    "village": "Shyamkalan",
    "slug": "shyamkalan",
    "city": "Ajitgarh",
    "state": "Punjab"
  },
  {
    "village": "Harikhas",
    "slug": "harikhas",
    "city": "Ajitgarh",
    "state": "Punjab"
  },
  {
    "village": "Agrakalan",
    "slug": "agrakalan",
    "city": "Hoshiarpur",
    "state": "Punjab"
  },
  {
    "village": "Belkhas",
    "slug": "belkhas",
    "city": "Hoshiarpur",
    "state": "Punjab"
  },
  {
    "village": "Kalyanbad",
    "slug": "kalyanbad",
    "city": "Hoshiarpur",
    "state": "Punjab"
  },
  {
    "village": "Vikaskhas",
    "slug": "vikaskhas",
    "city": "Pathankot",
    "state": "Punjab"
  },
  {
    "village": "Ashokbad",
    "slug": "ashokbad",
    "city": "Pathankot",
    "state": "Punjab"
  },
  {
    "village": "Premgarh",
    "slug": "premgarh",
    "city": "Pathankot",
    "state": "Punjab"
  },
  {
    "village": "Chandrabad",
    "slug": "chandrabad",
    "city": "Moga",
    "state": "Punjab"
  },
  {
    "village": "Suryagarh",
    "slug": "suryagarh",
    "city": "Moga",
    "state": "Punjab"
  },
  {
    "village": "Rajpur",
    "slug": "rajpur",
    "city": "Moga",
    "state": "Punjab"
  },
  {
    "village": "Motigarh",
    "slug": "motigarh",
    "city": "Abohar",
    "state": "Punjab"
  },
  {
    "village": "Rampur",
    "slug": "rampur",
    "city": "Abohar",
    "state": "Punjab"
  },
  {
    "village": "Gopalgaon",
    "slug": "gopalgaon",
    "city": "Abohar",
    "state": "Punjab"
  },
  {
    "village": "Shyampur",
    "slug": "shyampur",
    "city": "Malerkotla",
    "state": "Punjab"
  },
  {
    "village": "Harigaon",
    "slug": "harigaon",
    "city": "Malerkotla",
    "state": "Punjab"
  },
  {
    "village": "Agrakhera",
    "slug": "agrakhera",
    "city": "Malerkotla",
    "state": "Punjab"
  },
  {
    "village": "Belgaon",
    "slug": "belgaon",
    "city": "Khanna",
    "state": "Punjab"
  },
  {
    "village": "Kalyankhera",
    "slug": "kalyankhera",
    "city": "Khanna",
    "state": "Punjab"
  },
  {
    "village": "Vikaskhurd",
    "slug": "vikaskhurd",
    "city": "Khanna",
    "state": "Punjab"
  },
  {
    "village": "Ashokkhera",
    "slug": "ashokkhera",
    "city": "Phagwara",
    "state": "Punjab"
  },
  {
    "village": "Premkhurd",
    "slug": "premkhurd",
    "city": "Phagwara",
    "state": "Punjab"
  },
  {
    "village": "Chandrabuzurg",
    "slug": "chandrabuzurg",
    "city": "Phagwara",
    "state": "Punjab"
  },
  {
    "village": "Suryakhurd",
    "slug": "suryakhurd",
    "city": "Firozpur",
    "state": "Punjab"
  },
  {
    "village": "Rajbuzurg",
    "slug": "rajbuzurg",
    "city": "Firozpur",
    "state": "Punjab"
  },
  {
    "village": "Motinagar",
    "slug": "motinagar",
    "city": "Firozpur",
    "state": "Punjab"
  },
  {
    "village": "Rambuzurg",
    "slug": "rambuzurg",
    "city": "Kapurthala",
    "state": "Punjab"
  },
  {
    "village": "Gopalnagar",
    "slug": "gopalnagar",
    "city": "Kapurthala",
    "state": "Punjab"
  },
  {
    "village": "Shyamkalan",
    "slug": "shyamkalan",
    "city": "Kapurthala",
    "state": "Punjab"
  },
  {
    "village": "Harinagar",
    "slug": "harinagar",
    "city": "Ludhiana Block",
    "state": "Punjab"
  },
  {
    "village": "Agrakalan",
    "slug": "agrakalan",
    "city": "Ludhiana Block",
    "state": "Punjab"
  },
  {
    "village": "Belkhas",
    "slug": "belkhas",
    "city": "Ludhiana Block",
    "state": "Punjab"
  },
  {
    "village": "Kalyankalan",
    "slug": "kalyankalan",
    "city": "Amritsar Rural",
    "state": "Punjab"
  },
  {
    "village": "Vikaskhas",
    "slug": "vikaskhas",
    "city": "Amritsar Rural",
    "state": "Punjab"
  },
  {
    "village": "Ashokbad",
    "slug": "ashokbad",
    "city": "Amritsar Rural",
    "state": "Punjab"
  },
  {
    "village": "Premkhas",
    "slug": "premkhas",
    "city": "Jalandhar East",
    "state": "Punjab"
  },
  {
    "village": "Chandrabad",
    "slug": "chandrabad",
    "city": "Jalandhar East",
    "state": "Punjab"
  },
  {
    "village": "Suryagarh",
    "slug": "suryagarh",
    "city": "Jalandhar East",
    "state": "Punjab"
  },
  {
    "village": "Rajbad",
    "slug": "rajbad",
    "city": "Patiala West",
    "state": "Punjab"
  },
  {
    "village": "Motigarh",
    "slug": "motigarh",
    "city": "Patiala West",
    "state": "Punjab"
  },
  {
    "village": "Rampur",
    "slug": "rampur",
    "city": "Patiala West",
    "state": "Punjab"
  },
  {
    "village": "Gopalgarh",
    "slug": "gopalgarh",
    "city": "Bathinda North",
    "state": "Punjab"
  },
  {
    "village": "Shyampur",
    "slug": "shyampur",
    "city": "Bathinda North",
    "state": "Punjab"
  },
  {
    "village": "Harigaon",
    "slug": "harigaon",
    "city": "Bathinda North",
    "state": "Punjab"
  },
  {
    "village": "Agrapur",
    "slug": "agrapur",
    "city": "Ajitgarh South",
    "state": "Punjab"
  },
  {
    "village": "Belgaon",
    "slug": "belgaon",
    "city": "Ajitgarh South",
    "state": "Punjab"
  },
  {
    "village": "Kalyankhera",
    "slug": "kalyankhera",
    "city": "Ajitgarh South",
    "state": "Punjab"
  },
  {
    "village": "Vikasgaon",
    "slug": "vikasgaon",
    "city": "Hoshiarpur Central",
    "state": "Punjab"
  },
  {
    "village": "Ashokkhera",
    "slug": "ashokkhera",
    "city": "Hoshiarpur Central",
    "state": "Punjab"
  },
  {
    "village": "Premkhurd",
    "slug": "premkhurd",
    "city": "Hoshiarpur Central",
    "state": "Punjab"
  },
  {
    "village": "Chandrakhera",
    "slug": "chandrakhera",
    "city": "Pathankot Hills",
    "state": "Punjab"
  },
  {
    "village": "Suryakhurd",
    "slug": "suryakhurd",
    "city": "Pathankot Hills",
    "state": "Punjab"
  },
  {
    "village": "Rajbuzurg",
    "slug": "rajbuzurg",
    "city": "Pathankot Hills",
    "state": "Punjab"
  },
  {
    "village": "Motikhurd",
    "slug": "motikhurd",
    "city": "Moga Valley",
    "state": "Punjab"
  },
  {
    "village": "Rambuzurg",
    "slug": "rambuzurg",
    "city": "Moga Valley",
    "state": "Punjab"
  },
  {
    "village": "Gopalnagar",
    "slug": "gopalnagar",
    "city": "Moga Valley",
    "state": "Punjab"
  },
  {
    "village": "Shyambuzurg",
    "slug": "shyambuzurg",
    "city": "Abohar Uplands",
    "state": "Punjab"
  },
  {
    "village": "Harinagar",
    "slug": "harinagar",
    "city": "Abohar Uplands",
    "state": "Punjab"
  },
  {
    "village": "Agrakalan",
    "slug": "agrakalan",
    "city": "Abohar Uplands",
    "state": "Punjab"
  }
]